wlog/__init__.py
wlog/wlog.py
wlog-1.0.0.dist-info/METADATA
wlog-1.0.0.dist-info/WHEEL
wlog-1.0.0.dist-info/top_level.txt
wlog-1.0.0.dist-info/RECORD
