Metadata-Version: 2.1
Name: wlog
Version: 1.0.0
Summary: A log python project, logger
Home-page: https://github.com/fyingzhu/Python_logging
Author: fyingzhu
Author-email: fyingzhu@126.com
License: MIT
Keywords: log logger logging python
Platform: UNKNOWN
Classifier: Development Status :: 4 - Beta
Classifier: Intended Audience :: Developers
Classifier: Topic :: Software Development :: Build Tools
Classifier: License :: OSI Approved :: MIT License
Classifier: Programming Language :: Python :: 2.7
Classifier: Programming Language :: Python :: 3
Classifier: Programming Language :: Python :: 3.3
Classifier: Programming Language :: Python :: 3.4
Classifier: Programming Language :: Python :: 3.5
Classifier: Programming Language :: Python :: 3.6
Classifier: Programming Language :: Python :: 3.7
